{
  "componentDefinitions": [
    {
      "componentId": 674,
      "componentPosition": 1,
      "relationComponents": [],
      "partGroup": 0,
      "errorValue": "08",
      "showList": 1,
      "componentTypeId": 2,
      "componentDisplayName": "Shell Size",
      "partBuildPosition": 1,
      "useValueForPartNumberBuild": true,
      "optionItems": [
        {
          "valueId": 12559,
          "value": "08",
          "valueDisplay": "08",
          "groupValue": [],
          "specialPrefix": "",
          "partId": 0
        },
        {
          "valueId": 12560,
          "value": "10",
          "valueDisplay": "10",
          "groupValue": [],
          "specialPrefix": "",
          "partId": 0
        },
        {
          "valueId": 12561,
          "value": "12",
          "valueDisplay": "12",
          "groupValue": [],
          "specialPrefix": "",
          "partId": 0
        },
        {
          "valueId": 12562,
          "value": "14",
          "valueDisplay": "14",
          "groupValue": [],
          "specialPrefix": "",
          "partId": 0
        },
        {
          "valueId": 12563,
          "value": "16",
          "valueDisplay": "16",
          "groupValue": [],
          "specialPrefix": "",
          "partId": 0
        },
        {
          "valueId": 12564,
          "value": "18",
          "valueDisplay": "18",
          "groupValue": [],
          "specialPrefix": "",
          "partId": 0
        },
        {
          "valueId": 12565,
          "value": "20",
          "valueDisplay": "20",
          "groupValue": [],
          "specialPrefix": "",
          "partId": 0
        },
        {
          "valueId": 12566,
          "value": "22",
          "valueDisplay": "22",
          "groupValue": [],
          "specialPrefix": "",
          "partId": 0
        },
        {
          "valueId": 12567,
          "value": "24",
          "valueDisplay": "24",
          "groupValue": [],
          "specialPrefix": "",
          "partId": 0
        }
      ]
    },
    {
      "componentId": 675,
      "componentPosition": 2,
      "relationComponents": [
        674
      ],
      "partGroup": 0,
      "showList": 1,
      "componentTypeId": 97,
      "componentDisplayName": "Cable Entry MAX",
      "partBuildPosition": 3,
      "useValueForPartNumberBuild": true,
      "optionItems": [
        {
          "valueId": 16114,
          "value": "01",
          "valueDisplay": ".125 (3.2)",
          "groupValue": [
            "08"
          ],
          "specialPrefix": "",
          "partId": 0
        },
        {
          "valueId": 16115,
          "value": "02",
          "valueDisplay": ".250 (6.4)",
          "groupValue": [
            "08"
          ],
          "specialPrefix": "",
          "partId": 0
        },
        {
          "valueId": 16116,
          "value": "01",
          "valueDisplay": ".125 (3.2)",
          "groupValue": [
            "10"
          ],
          "specialPrefix": "",
          "partId": 0
        },
        {
          "valueId": 16117,
          "value": "02",
          "valueDisplay": ".250 (6.4)",
          "groupValue": [
            "10"
          ],
          "specialPrefix": "",
          "partId": 0
        },
        {
          "valueId": 16118,
          "value": "03",
          "valueDisplay": ".375 (9.5)",
          "groupValue": [
            "10"
          ],
          "specialPrefix": "",
          "partId": 0
        },
        {
          "valueId": 16119,
          "value": "02",
          "valueDisplay": ".250 (6.4)",
          "groupValue": [
            "12"
          ],
          "specialPrefix": "",
          "partId": 0
        },
        {
          "valueId": 16120,
          "value": "03",
          "valueDisplay": ".375 (9.5)",
          "groupValue": [
            "12"
          ],
          "specialPrefix": "",
          "partId": 0
        },
        {
          "valueId": 16121,
          "value": "04",
          "valueDisplay": ".500 (12.7)",
          "groupValue": [
            "12"
          ],
          "specialPrefix": "",
          "partId": 0
        },
        {
          "valueId": 16122,
          "value": "02",
          "valueDisplay": ".250 (6.4)",
          "groupValue": [
            "14"
          ],
          "specialPrefix": "",
          "partId": 0
        },
        {
          "valueId": 16123,
          "value": "03",
          "valueDisplay": ".375 (9.5)",
          "groupValue": [
            "14"
          ],
          "specialPrefix": "",
          "partId": 0
        },
        {
          "valueId": 16124,
          "value": "04",
          "valueDisplay": ".500 (12.7)",
          "groupValue": [
            "14"
          ],
          "specialPrefix": "",
          "partId": 0
        },
        {
          "valueId": 16125,
          "value": "05",
          "valueDisplay": ".625 (15.9)",
          "groupValue": [
            "14"
          ],
          "specialPrefix": "",
          "partId": 0
        },
        {
          "valueId": 16126,
          "value": "02",
          "valueDisplay": ".250 (6.4)",
          "groupValue": [
            "16"
          ],
          "specialPrefix": "",
          "partId": 0
        },
        {
          "valueId": 16127,
          "value": "03",
          "valueDisplay": ".375 (9.5)",
          "groupValue": [
            "16"
          ],
          "specialPrefix": "",
          "partId": 0
        },
        {
          "valueId": 16128,
          "value": "04",
          "valueDisplay": ".500 (12.7)",
          "groupValue": [
            "16"
          ],
          "specialPrefix": "",
          "partId": 0
        },
        {
          "valueId": 16129,
          "value": "05",
          "valueDisplay": ".625 (15.9)",
          "groupValue": [
            "16"
          ],
          "specialPrefix": "",
          "partId": 0
        },
        {
          "valueId": 16130,
          "value": "06",
          "valueDisplay": ".750 (19.1)",
          "groupValue": [
            "16"
          ],
          "specialPrefix": "",
          "partId": 0
        },
        {
          "valueId": 16131,
          "value": "03",
          "valueDisplay": ".375 (9.5)",
          "groupValue": [
            "18"
          ],
          "specialPrefix": "",
          "partId": 0
        },
        {
          "valueId": 16132,
          "value": "04",
          "valueDisplay": ".500 (12.7)",
          "groupValue": [
            "18"
          ],
          "specialPrefix": "",
          "partId": 0
        },
        {
          "valueId": 16133,
          "value": "05",
          "valueDisplay": ".625 (15.9)",
          "groupValue": [
            "18"
          ],
          "specialPrefix": "",
          "partId": 0
        },
        {
          "valueId": 16134,
          "value": "06",
          "valueDisplay": ".750 (19.1)",
          "groupValue": [
            "18"
          ],
          "specialPrefix": "",
          "partId": 0
        },
        {
          "valueId": 16135,
          "value": "03",
          "valueDisplay": ".375 (9.5)",
          "groupValue": [
            "20"
          ],
          "specialPrefix": "",
          "partId": 0
        },
        {
          "valueId": 16136,
          "value": "04",
          "valueDisplay": ".500 (12.7)",
          "groupValue": [
            "20"
          ],
          "specialPrefix": "",
          "partId": 0
        },
        {
          "valueId": 16137,
          "value": "05",
          "valueDisplay": ".625 (15.9)",
          "groupValue": [
            "20"
          ],
          "specialPrefix": "",
          "partId": 0
        },
        {
          "valueId": 16138,
          "value": "06",
          "valueDisplay": ".750 (19.1)",
          "groupValue": [
            "20"
          ],
          "specialPrefix": "",
          "partId": 0
        },
        {
          "valueId": 16139,
          "value": "07",
          "valueDisplay": ".875 (22.2)",
          "groupValue": [
            "20"
          ],
          "specialPrefix": "",
          "partId": 0
        },
        {
          "valueId": 16140,
          "value": "03",
          "valueDisplay": ".375 (9.5)",
          "groupValue": [
            "22"
          ],
          "specialPrefix": "",
          "partId": 0
        },
        {
          "valueId": 16141,
          "value": "04",
          "valueDisplay": ".500 (12.7)",
          "groupValue": [
            "22"
          ],
          "specialPrefix": "",
          "partId": 0
        },
        {
          "valueId": 16142,
          "value": "05",
          "valueDisplay": ".625 (15.9)",
          "groupValue": [
            "22"
          ],
          "specialPrefix": "",
          "partId": 0
        },
        {
          "valueId": 16143,
          "value": "06",
          "valueDisplay": ".750 (19.1)",
          "groupValue": [
            "22"
          ],
          "specialPrefix": "",
          "partId": 0
        },
        {
          "valueId": 16144,
          "value": "07",
          "valueDisplay": ".875 (22.2)",
          "groupValue": [
            "22"
          ],
          "specialPrefix": "",
          "partId": 0
        },
        {
          "valueId": 16145,
          "value": "08",
          "valueDisplay": "1.000 (25.4)",
          "groupValue": [
            "22"
          ],
          "specialPrefix": "",
          "partId": 0
        },
        {
          "valueId": 16146,
          "value": "04",
          "valueDisplay": ".500 (12.7)",
          "groupValue": [
            "24"
          ],
          "specialPrefix": "",
          "partId": 0
        },
        {
          "valueId": 16147,
          "value": "05",
          "valueDisplay": ".625 (15.9)",
          "groupValue": [
            "24"
          ],
          "specialPrefix": "",
          "partId": 0
        },
        {
          "valueId": 16148,
          "value": "06",
          "valueDisplay": ".750 (19.1)",
          "groupValue": [
            "24"
          ],
          "specialPrefix": "",
          "partId": 0
        },
        {
          "valueId": 16149,
          "value": "07",
          "valueDisplay": ".875 (22.2)",
          "groupValue": [
            "24"
          ],
          "specialPrefix": "",
          "partId": 0
        },
        {
          "valueId": 16150,
          "value": "08",
          "valueDisplay": "1.000 (25.4)",
          "groupValue": [
            "24"
          ],
          "specialPrefix": "",
          "partId": 0
        },
        {
          "valueId": 16151,
          "value": "09",
          "valueDisplay": "1.125 (28.6)",
          "groupValue": [
            "24"
          ],
          "specialPrefix": "",
          "partId": 0
        },
        {
          "valueId": 16152,
          "value": "07",
          "valueDisplay": ".875 (22.2)",
          "groupValue": [],
          "specialPrefix": "",
          "partId": 0
        },
        {
          "valueId": 16153,
          "value": "08",
          "valueDisplay": "1.000 (25.4)",
          "groupValue": [],
          "specialPrefix": "",
          "partId": 0
        },
        {
          "valueId": 16154,
          "value": "09",
          "valueDisplay": "1.125 (28.6)",
          "groupValue": [],
          "specialPrefix": "",
          "partId": 0
        },
        {
          "valueId": 16155,
          "value": "10",
          "valueDisplay": "1.250 (31.8)",
          "groupValue": [],
          "specialPrefix": "",
          "partId": 0
        }
      ]
    },
    {
      "componentId": 676,
      "componentPosition": 3,
      "relationComponents": [],
      "partGroup": 0,
      "showList": 1,
      "componentTypeId": 4,
      "componentDisplayName": "Finish",
      "partBuildPosition": 2,
      "useValueForPartNumberBuild": true,
      "optionItems": [
        {
          "valueId": 16397,
          "value": "N",
          "valueDisplay": "Aluminum/Electroless Nickel",
          "groupValue": [],
          "specialPrefix": "",
          "partId": 0
        },
        {
          "valueId": 16398,
          "value": "W",
          "valueDisplay": "Aluminum/Cadmium over Electroless Nickel",
          "groupValue": [],
          "specialPrefix": "",
          "partId": 0
        }
      ]
    },
    {
      "componentId": 677,
      "componentPosition": 4,
      "relationComponents": [],
      "partGroup": 0,
      "showList": 1,
      "componentTypeId": 98,
      "componentDisplayName": "Hole Option",
      "partBuildPosition": 4,
      "useValueForPartNumberBuild": true,
      "optionItems": [
        {
          "valueId": 16449,
          "value": "D",
          "valueDisplay": "3 Drain Holes",
          "groupValue": [],
          "specialPrefix": "",
          "partId": 0
        },
        {
          "valueId": 16450,
          "value": "L",
          "valueDisplay": "Encapsulating Hole",
          "groupValue": [],
          "specialPrefix": "",
          "partId": 0
        }
      ]
    }
  ],
  "productRightHandMetadataDefinitions": [
    {
      "label": "Connector Shell Size",
      "componentId": 674,
      "componentTypeId": 203,
      "displayLevel": 1,
      "isDimension": 0,
      "metaDataValues": []
    },
    {
      "label": "Series I",
      "componentId": 674,
      "componentTypeId": 302,
      "displayLevel": 2,
      "isDimension": 1,
      "metaDataValues": [
        {
          "dimensionValue": "08",
          "value": "9"
        },
        {
          "dimensionValue": "10",
          "value": "11"
        },
        {
          "dimensionValue": "12",
          "value": "13"
        },
        {
          "dimensionValue": "14",
          "value": "15"
        },
        {
          "dimensionValue": "16",
          "value": "17"
        },
        {
          "dimensionValue": "18",
          "value": "19"
        },
        {
          "dimensionValue": "20",
          "value": "21"
        },
        {
          "dimensionValue": "22",
          "value": "23"
        },
        {
          "dimensionValue": "24",
          "value": "25"
        }
      ]
    },
    {
      "label": "Series II",
      "componentId": 674,
      "componentTypeId": 303,
      "displayLevel": 2,
      "isDimension": 1,
      "metaDataValues": [
        {
          "dimensionValue": "08",
          "value": "8"
        },
        {
          "dimensionValue": "10",
          "value": "10"
        },
        {
          "dimensionValue": "12",
          "value": "12"
        },
        {
          "dimensionValue": "14",
          "value": "14"
        },
        {
          "dimensionValue": "16",
          "value": "16"
        },
        {
          "dimensionValue": "18",
          "value": "18"
        },
        {
          "dimensionValue": "20",
          "value": "20"
        },
        {
          "dimensionValue": "22",
          "value": "22"
        },
        {
          "dimensionValue": "24",
          "value": "24"
        }
      ]
    },
    {
      "label": "Connector Interface Thread Size",
      "componentId": 674,
      "componentTypeId": 277,
      "displayLevel": 1,
      "isDimension": 1,
      "metaDataValues": [
        {
          "dimensionValue": "08",
          "value": ".438 - 28 UNEF"
        },
        {
          "dimensionValue": "10",
          "value": ".562 - 24 UNEF"
        },
        {
          "dimensionValue": "12",
          "value": ".688 - 24 UNEF"
        },
        {
          "dimensionValue": "14",
          "value": ".813 - 20 UNEF"
        },
        {
          "dimensionValue": "16",
          "value": ".938 - 20 UNEF"
        },
        {
          "dimensionValue": "18",
          "value": "1.063 - 18 UNEF"
        },
        {
          "dimensionValue": "20",
          "value": "1.188 - 18 UNEF"
        },
        {
          "dimensionValue": "22",
          "value": "1.313 - 18 UNEF"
        },
        {
          "dimensionValue": "24",
          "value": "1.438 - 18 UNEF"
        }
      ]
    },
    {
      "label": "CABLE RANGE",
      "componentId": 675,
      "componentTypeId": 225,
      "displayLevel": 1,
      "isDimension": 0,
      "metaDataValues": []
    },
    {
      "label": "MAX",
      "componentId": 675,
      "componentTypeId": 115,
      "displayLevel": 2,
      "isDimension": 1,
      "metaDataValues": [
        {
          "dimensionValue": "01",
          "value": ".125 (3.2)"
        },
        {
          "dimensionValue": "02",
          "value": ".250 (6.4)"
        },
        {
          "dimensionValue": "03",
          "value": ".375 (9.5)"
        },
        {
          "dimensionValue": "04",
          "value": ".500 (12.7)"
        },
        {
          "dimensionValue": "05",
          "value": ".625 (15.9)"
        },
        {
          "dimensionValue": "06",
          "value": ".750 (19.1)"
        },
        {
          "dimensionValue": "07",
          "value": ".875 (22.2)"
        },
        {
          "dimensionValue": "08",
          "value": "1.000 (25.4)"
        },
        {
          "dimensionValue": "09",
          "value": "1.125 (28.6)"
        }
      ]
    },
    {
      "label": "MIN",
      "componentId": 675,
      "componentTypeId": 114,
      "displayLevel": 2,
      "isDimension": 1,
      "metaDataValues": [
        {
          "dimensionValue": "01",
          "value": ".062 (1.6)"
        },
        {
          "dimensionValue": "02",
          "value": ".125 (3.2)"
        },
        {
          "dimensionValue": "03",
          "value": ".250 (6.4)"
        },
        {
          "dimensionValue": "04",
          "value": ".312 (7.9)"
        },
        {
          "dimensionValue": "05",
          "value": ".437 (11.1)"
        },
        {
          "dimensionValue": "06",
          "value": ".562 (14.3)"
        },
        {
          "dimensionValue": "07",
          "value": ".687 (17.4)"
        },
        {
          "dimensionValue": "08",
          "value": ".812 (20.6)"
        },
        {
          "dimensionValue": "09",
          "value": ".937 (23.8)"
        }
      ]
    },
    {
      "label": "Plating",
      "componentId": 676,
      "componentTypeId": 40,
      "displayLevel": 1,
      "isDimension": 1,
      "metaDataValues": [
        {
          "dimensionValue": "A",
          "value": "Aluminum/Black Anodize"
        },
        {
          "dimensionValue": "B",
          "value": "CRES/Black Cadmium"
        },
        {
          "dimensionValue": "W",
          "value": "Aluminum/Cadmium over Electroless Nickel"
        },
        {
          "dimensionValue": "N",
          "value": "Aluminum/Electroless Nickel"
        },
        {
          "dimensionValue": "S",
          "value": "CRES/Passivated"
        },
        {
          "dimensionValue": "P",
          "value": "Aluminum/Cadmium over Electroless Nickel w/Polysulfide Sealant Strips"
        }
      ]
    }
  ],
  "productLeftHandMetadataDefinitions": [
    {
      "componentTypeId": 2,
      "label": "Shell Size",
      "componentId": 674,
      "suffixDescription": "",
      "prefixDescription": "",
      "useDisplayTextForMetadata": 0,
      "useValueAndTextForMetaData": 0,
      "useForPartDesc": true,
      "displayLevel": 1
    },
    {
      "componentTypeId": 86,
      "label": "Finish Code",
      "componentId": 676,
      "suffixDescription": "",
      "prefixDescription": "",
      "useDisplayTextForMetadata": 0,
      "useValueAndTextForMetaData": 0,
      "useForPartDesc": false,
      "displayLevel": 1
    },
    {
      "componentTypeId": 224,
      "label": "CLAMP SIZE",
      "componentId": 675,
      "suffixDescription": "",
      "prefixDescription": "",
      "useDisplayTextForMetadata": 0,
      "useValueAndTextForMetaData": 0,
      "useForPartDesc": true,
      "displayLevel": 1
    },
    {
      "componentTypeId": 98,
      "label": "Hole Option",
      "componentId": 677,
      "suffixDescription": "Supplied",
      "prefixDescription": "",
      "useDisplayTextForMetadata": 1,
      "useValueAndTextForMetaData": 0,
      "useForPartDesc": true,
      "displayLevel": 1
    }
  ],
  "partNotes": [
    {
      "messageCode": 17,
      "message": "Metric Dimensions are shown in ( ) parentheses for reference only."
    }
  ],
  "errorConditions": []
}